cached_fields/__init__.py
cached_fields/exceptions.py
cached_fields/fields.py
cached_fields/handlers.py
cached_fields/mixins.py
django_cached_fields-0.1.2.dist-info/LICENSE
django_cached_fields-0.1.2.dist-info/METADATA
django_cached_fields-0.1.2.dist-info/WHEEL
django_cached_fields-0.1.2.dist-info/top_level.txt
django_cached_fields-0.1.2.dist-info/RECORD
